bugdoc/__init__.py
bugdoc/algos/__init__.py
bugdoc/algos/debugging_decision_trees.py
bugdoc/algos/minimal_pairs.py
bugdoc/algos/shortcut.py
bugdoc/algos/stacked_shortcut.py
bugdoc/utils/__init__.py
bugdoc/utils/combinatorial_design.py
bugdoc/utils/quine_mccluskey.py
bugdoc/utils/tree.py
bugdoc/utils/utils.py
bugdoc-0.1.dist-info/METADATA
bugdoc-0.1.dist-info/WHEEL
bugdoc-0.1.dist-info/top_level.txt
bugdoc-0.1.dist-info/RECORD
