Metadata-Version: 2.1
Name: bugdoc
Version: 0.1
Summary: BugDoc library
Home-page: UNKNOWN
Author: Raoni Lourenco
Author-email: raoni@nyu.edu
Maintainer: Raoni Lourenco
Maintainer-email: raoni@nyu.edu
License: UNKNOWN
Keywords: Scientific Workflows,Provenance,Heuristic Algorithms,Debugging,Combinatorial Design,Parameter Exploration
Platform: UNKNOWN
Requires-Dist: pytest-cov
Requires-Dist: pylint
Requires-Dist: future
Requires-Dist: numpy
Requires-Dist: zmq
Requires-Dist: certifi (>=2017.4.17)
Requires-Dist: Pillow
Requires-Dist: image
Requires-Dist: nose (==1.3.7)
Requires-Dist: Django (==1.11.28)
